<ConditionalActions>
	<OnConnect target="NHHub" needsMissionComplete="false">
	<AddConditionalActions Filepath="Actions/Act 2/Veng/Flag.xml" DelayHost="Delay" Delay="100.0"/>
	<ChangeAlertIcon Target="NHHub" Type="irchub" DelayHost="Delay" Delay="0.0"/>
	<AddIRCMessage Author="Vortex" TargetComp="NHHub" Delay="5.0">@channel, 我有Omicron的位置文件!我们可以解密它了!</AddIRCMessage>
	<AddIRCMessage Author="Maverick" TargetComp="NHHub" Delay="10.0">不,你自己解密它,我们对伤害我们的捐助者不感兴趣</AddIRCMessage>
	<AddIRCMessage Author="Vortex" TargetComp="NHHub" Delay="15.0">你一定要帮我!该死!</AddIRCMessage>
	<AddIRCMessage Author="Vortex" TargetComp="NHHub" Delay="18.0">我需要他死!</AddIRCMessage>
	<AddIRCMessage Author="Vortex" TargetComp="NHHub" Delay="23.0">我为你打开资产服务器!</AddIRCMessage>
	<AddIRCMessage Author="Vortex" TargetComp="NHHub" Delay="26.0">而你们也应付出代价!</AddIRCMessage>
	<AddIRCMessage Author="Prophet" TargetComp="NHHub" Delay="31.0">我也帮了你</AddIRCMessage>
	<AddIRCMessage Author="Deladello" TargetComp="NHHub" Delay="35.0">我们都以一种或另一种方式做出了贡献</AddIRCMessage>
	<AddIRCMessage Author="Deladello" TargetComp="NHHub" Delay="39.0">如果不是我们给你这次机会,你甚至都不会遇到Omicron</AddIRCMessage>
	<AddIRCMessage Author="Maverick" TargetComp="NHHub" Delay="44.0">所以是你应该尊重我们</AddIRCMessage>
	<AddIRCMessage Author="Maverick" TargetComp="NHHub" Delay="48.0">让我们细数下你都干了啥</AddIRCMessage>
	<AddConditionalActions Filepath="Actions/Act 2/Choices/1.xml" DelayHost="Delay" Delay="52.0"/>
	<AddIRCMessage Author="Maverick" TargetComp="NHHub" Delay="57.0">导致了"良好"的合同统计</AddIRCMessage>
	<AddConditionalActions Filepath="Actions/Act 2/Choices/2.xml" DelayHost="Delay" Delay="62.0"/>
	<AddConditionalActions Filepath="Actions/Act 2/Choices/3.xml" DelayHost="Delay" Delay="67.0"/>
	<AddIRCMessage Author="Maverick" TargetComp="NHHub" Delay="72.0">最终获得了Omicron的位置文件</AddIRCMessage>
	<AddIRCMessage Author="Maverick" TargetComp="NHHub" Delay="77.0">你内心有些胆怯,但我们将不再是合作伙伴</AddIRCMessage>
	<AddIRCMessage Author="Maverick" TargetComp="NHHub" Delay="81.0">至少由于你的警察出身</AddIRCMessage>
	<AddIRCMessage Author="Maverick" TargetComp="NHHub" Delay="85.0">尽管我们会采取最后一步来帮助你,并且会解密该位置文件</AddIRCMessage>
	<AddIRCMessage Author="Maverick" TargetComp="NHHub" Delay="90.0">然后,你可以与Omicron搏斗,而毫无机会获胜</AddIRCMessage>
	<AddIRCMessage Author="Maverick" TargetComp="NHHub" Delay="95.0">Jenkins, 解决它</AddIRCMessage>
	<AddIRCMessage Author="Jenkins" TargetComp="NHHub" Delay="100.0">@Vortex, 将位置文件放在此服务器的/home文件夹中</AddIRCMessage>
	<ChangeAlertIcon Target="M6Alert" Type="board" DelayHost="Delay" Delay="100.1"/>
		<AddConditionalActions Filepath="Actions/Act 2/Mission 6/Hid2.xml" DelayHost="Delay" Delay="100.2"/>
		<ChangeAlertIcon Target="NHHub" Type="irchub" DelayHost="Delay" Delay="100.3"/>
	</OnConnect>
</ConditionalActions>