<?xml version = "1.0" encoding = "UTF-8" ?>
<mission id="M8 1 R">
  <goals>
<goal type="fileupload" target="NHCrossR" file="Fin-Rep.accdb" path="home/Contract_Files/Data_Manipulation" destTarget="C1C" destPath="home/11_19"/>
  </goals>
  <missionEnd val="1">addRankSilent</missionEnd>
  <nextMission>NONE</nextMission>
  <posting title="数据处理">
某些文档必须放置在不应放置的位置
  </posting>
  <email>
    <sender>E-Mail</sender>
    <subject>数据处理</subject>
    <body>此电子邮件由从外部收件箱接收：

您好，探员，我有一个任务交给你。我需要淘汰我的商业竞争对手，使其与突如其来的税务检查相撞。我需要您在公司的财务服务器上植入一些报告，其中包含一些“未说明的费用”，该报告应该在11_19文件夹中。

您可以在组织的Crossroads服务器上找到Fin-Rep.accdb文件，我拥有他们的人力资源部门的IP，您可以从那里浏览他们的系统。
目标:

1) 上传Fin-Rep.accdb至Rezik company的数据服务器中的11_19文件夹
</body>
    <attachments>
	<link comp="C1A" />
    </attachments>
  </email>
</mission>